clgenomics/__init__.py
clgenomics/metrics.py
clgenomics/adapters/__init__.py
clgenomics/adapters/base.py
clgenomics/adapters/peft.py
clgenomics/learners/__init__.py
clgenomics/learners/base.py
clgenomics/learners/demo.py
clgenomics/learners/regularize.py
clgenomics/learners/replay.py
clgenomics/losses/__init__.py
clgenomics/losses/common.py
clgenomics/losses/contrastive.py
clgenomics/models/__init__.py
clgenomics/models/utils.py
clgenomics/models/bases/__init__.py
clgenomics/models/bases/borzoi.py
clgenomics/models/bases/bpnet.py
clgenomics/models/bases/enformer.py
clgenomics/models/heads/__init__.py
clgenomics/models/heads/avgpoollinear.py
clgenomics/models/heads/base.py
clgenomics/models/heads/borzoi.py
clgenomics/models/heads/demo.py
clgenomics/models/heads/enformer.py
clgenomics/models/heads/profilecount.py
clgenomics/utils/__init__.py
clgenomics/utils/data.py
clgenomics/utils/deps.py
clgenomics-0.1.1.dist-info/METADATA
clgenomics-0.1.1.dist-info/WHEEL
clgenomics-0.1.1.dist-info/top_level.txt
clgenomics-0.1.1.dist-info/RECORD
