Metadata-Version: 2.4
Name: clgenomics
Version: 0.1.1
Summary: Continual learning for genomics AI
Author-email: Masayuki Nagai <moon.masayukinagai@gmail.com>, Alan Murphy <alanmurph94@hotmail.com>
Project-URL: Homepage, https://github.com/MasayukiNagai/clgenomics
Classifier: Programming Language :: Python :: 3
Classifier: Operating System :: OS Independent
Requires-Python: >=3.10
Requires-Dist: numpy>=2.2.6
Requires-Dist: pytorch-lightning>=2.5.0
Requires-Dist: scipy>=1.15.3
Requires-Dist: torch>=2.6.0
Provides-Extra: borzoi
Requires-Dist: borzoi-pytorch>=0.4.4; extra == "borzoi"
Provides-Extra: enformer
Requires-Dist: enformer-pytorch>=0.8.10; extra == "enformer"
Provides-Extra: all
Requires-Dist: clgenomics[borzoi,enformer]; extra == "all"
